SC16IS750/SC16IS750.py
SC16IS750/__init__.py
driverSC16IS750-0.1.3.dist-info/METADATA
driverSC16IS750-0.1.3.dist-info/RECORD
driverSC16IS750-0.1.3.dist-info/WHEEL
driverSC16IS750-0.1.3.dist-info/top_level.txt
