Metadata-Version: 2.1
Name: driverSC16IS750
Version: 0.1.3
Summary: Python driver for interfacing with SC16IS750 I2C chip
Home-page: https://github.com/Harri-Renney/SC16IS750.git
Author: Harri Renney
Author-email: harri.renney@blino.co.uk
License: UNKNOWN
Platform: UNKNOWN
